demo
pfrock
